AUTHORS.rst
CHANGELOG.rst
LICENSE
MANIFEST.in
README.rst
setup.py
ckeditor/__init__.py
ckeditor/fields.py
ckeditor/models.py
ckeditor/tests.py
ckeditor/urls.py
ckeditor/views.py
ckeditor/widgets.py
ckeditor/static/ckeditor/.htaccess
ckeditor/static/ckeditor/ckeditor/CHANGES.html
ckeditor/static/ckeditor/ckeditor/INSTALL.html
ckeditor/static/ckeditor/ckeditor/LICENSE.html
ckeditor/static/ckeditor/ckeditor/ckeditor.asp
ckeditor/static/ckeditor/ckeditor/ckeditor.js
ckeditor/static/ckeditor/ckeditor/ckeditor.pack
ckeditor/static/ckeditor/ckeditor/ckeditor.php
ckeditor/static/ckeditor/ckeditor/ckeditor_basic.js
ckeditor/static/ckeditor/ckeditor/ckeditor_basic_source.js
ckeditor/static/ckeditor/ckeditor/ckeditor_php4.php
ckeditor/static/ckeditor/ckeditor/ckeditor_php5.php
ckeditor/static/ckeditor/ckeditor/ckeditor_source.js
ckeditor/static/ckeditor/ckeditor/ckpackager.jar
ckeditor/static/ckeditor/ckeditor/config.js
ckeditor/static/ckeditor/ckeditor/contents.css
ckeditor/static/ckeditor/ckeditor/_samples/ajax.html
ckeditor/static/ckeditor/ckeditor/_samples/api.html
ckeditor/static/ckeditor/ckeditor/_samples/api_dialog.html
ckeditor/static/ckeditor/ckeditor/_samples/autogrow.html
ckeditor/static/ckeditor/ckeditor/_samples/bbcode.html
ckeditor/static/ckeditor/ckeditor/_samples/devtools.html
ckeditor/static/ckeditor/ckeditor/_samples/divreplace.html
ckeditor/static/ckeditor/ckeditor/_samples/enterkey.html
ckeditor/static/ckeditor/ckeditor/_samples/fullpage.html
ckeditor/static/ckeditor/ckeditor/_samples/index.html
ckeditor/static/ckeditor/ckeditor/_samples/jqueryadapter.html
ckeditor/static/ckeditor/ckeditor/_samples/output_for_flash.html
ckeditor/static/ckeditor/ckeditor/_samples/output_html.html
ckeditor/static/ckeditor/ckeditor/_samples/output_xhtml.html
ckeditor/static/ckeditor/ckeditor/_samples/placeholder.html
ckeditor/static/ckeditor/ckeditor/_samples/readonly.html
ckeditor/static/ckeditor/ckeditor/_samples/replacebyclass.html
django_ckeditor_fc.egg-info/PKG-INFO
django_ckeditor_fc.egg-info/SOURCES.txt
django_ckeditor_fc.egg-info/dependency_links.txt
django_ckeditor_fc.egg-info/not-zip-safe
django_ckeditor_fc.egg-info/requires.txt
django_ckeditor_fc.egg-info/top_level.txt