Metadata-Version: 1.1
Name: django-ckeditor-fc
Version: 1.1
Summary: Django admin CKEditor integration.
Home-page: https://github.com/futurecolors/django-ckeditor
Author: Future Colors (orginal author:Shaun Sephton)
Author-email: shaunsephton@gmail.com
License: UNKNOWN
Platform: UNKNOWN
Classifier: Programming Language :: Python
Classifier: License :: OSI Approved :: BSD License
Classifier: Development Status :: 4 - Beta
Classifier: Operating System :: OS Independent
Classifier: Framework :: Django
Classifier: Intended Audience :: Developers
Classifier: Topic :: Internet :: WWW/HTTP :: Dynamic Content
